biochatter/__init__.py
biochatter/_image.py
biochatter/_misc.py
biochatter/_stats.py
biochatter/api_agent/__init__.py
biochatter/api_agent/base/__init__.py
biochatter/api_agent/base/_python_interpreter.py
biochatter/api_agent/base/agent_abc.py
biochatter/api_agent/base/api_agent.py
biochatter/api_agent/base/formatters.py
biochatter/api_agent/base/utils.py
biochatter/api_agent/data_model_generator/__init__.py
biochatter/api_agent/data_model_generator/data_model.jinja
biochatter/api_agent/data_model_generator/gen_data_model.py
biochatter/api_agent/dep_discovery/API_chains.py
biochatter/api_agent/dep_discovery/TODO.md
biochatter/api_agent/dep_discovery/__init__.py
biochatter/api_agent/dep_discovery/dep_finder.py
biochatter/api_agent/dep_discovery/results/scanpy_api_dep/SCANPY_PL_MULTI_LINE_SIMPLE_ARG_10-04-25.json
biochatter/api_agent/dep_discovery/results/scanpy_api_dep/SCANPY_PL_MULTI_LINE_SIMPLE_ARG_14-04-25.json
biochatter/api_agent/dep_discovery/results/scanpy_api_dep/SCANPY_PL_MULTI_LINE_SIMPLE_ARG_16-04-25/data.json
biochatter/api_agent/dep_discovery/results/scanpy_api_dep/SCANPY_PL_MULTI_LINE_SIMPLE_ARG_16-04-25/graph.json
biochatter/api_agent/dep_discovery/results/scanpy_api_dep/SCANPY_PL_MULTI_LINE_SIMPLE_ARG_16-04-25/graph.pkl
biochatter/api_agent/dep_discovery/results/scanpy_api_dep/SCANPY_PL_MULTI_LINE_SIMPLE_ARG_19-04-25/data.json
biochatter/api_agent/dep_discovery/results/scanpy_api_dep/SCANPY_PL_MULTI_LINE_SIMPLE_ARG_19-04-25/graph.json
biochatter/api_agent/dep_discovery/results/scanpy_api_dep/SCANPY_PL_MULTI_LINE_SIMPLE_ARG_19-04-25/graph.pkl
biochatter/api_agent/dep_discovery/results/scanpy_api_dep/SCANPY_PL_MULTI_LINE_SIMPLE_ARG_19-04-25_1/README.md
biochatter/api_agent/dep_discovery/results/scanpy_api_dep/SCANPY_PL_MULTI_LINE_SIMPLE_ARG_19-04-25_1/data.json
biochatter/api_agent/dep_discovery/results/scanpy_api_dep/SCANPY_PL_MULTI_LINE_SIMPLE_ARG_19-04-25_1/graph.json
biomania_backend-0.10.4.dist-info/LICENSE
biomania_backend-0.10.4.dist-info/METADATA
biomania_backend-0.10.4.dist-info/WHEEL
biomania_backend-0.10.4.dist-info/RECORD
